youtubedanyukla.py
youtubedanyukla-0.0.1.dist-info/WHEEL
youtubedanyukla-0.0.1.dist-info/METADATA
youtubedanyukla-0.0.1.dist-info/RECORD
