Metadata-Version: 2.1
Name: youtubedanyukla
Version: 0.0.1
Summary: Ushbu kutubxona yordamida Youtubedan videolarni osonlik bilan yuklab olishingiz mumkin!
Author: YusupovDeveloper
Requires-Python: >=3.8,<4.0
Classifier: Programming Language :: Python :: 3
Classifier: Programming Language :: Python :: 3.8
Classifier: Programming Language :: Python :: 3.9
Classifier: Programming Language :: Python :: 3.10
Requires-Dist: pytube (>=12.1.0,<13.0.0)
